{
    "013-4421": {
        "url": "/notice/013-4421",
        "title": "Grant Castle Corp.\n      \n         - Environmental Compliance Approval (sewage)",
        "comments_from_registry": 0,
        "comments_by_email": 0,
        "comments_by_mail": 0
    },
    "013-3344": {
        "url": "/notice/013-3344",
        "title": "KNL Developments Inc\n      \n         - Environmental Compliance Approval (sewage)",
        "comments_from_registry": 1,
        "comments_by_email": 0,
        "comments_by_mail": 0
    },
    "013-3343": {
        "url": "/notice/013-3343",
        "title": "KNL Developments Inc.\n      \n         - Environmental Compliance Approval (sewage)",
        "comments_from_registry": 1,
        "comments_by_email": 0,
        "comments_by_mail": 0
    },
    "013-5091": {
        "url": "/notice/013-5091",
        "title": "Huron Pines Golf and Country Club Inc.\n      \n         - Permit to take water",
        "comments_from_registry": 0,
        "comments_by_email": 0,
        "comments_by_mail": 0
    },
    "013-3254": {
        "url": "/notice/013-3254",
        "title": "Kirkland Lake Power Corp.\n      \n         - Permit to take water",
        "comments_from_registry": 0,
        "comments_by_email": 0,
        "comments_by_mail": 0
    },
    "013-5034": {
        "url": "/notice/013-5034",
        "title": "Glenn Kasner (Agent for Brian Bishop)\n      \n         - Mineral exploration permit",
        "comments_from_registry": 0,
        "comments_by_email": 0,
        "comments_by_mail": 0
    },
    "013-4746": {
        "url": "/notice/013-4746",
        "title": "Dowler-Karn Limited \n      \n         - Environmental Compliance Approval (sewage)",
        "comments_from_registry": 0,
        "comments_by_email": 0,
        "comments_by_mail": 0
    },
    "013-4738": {
        "url": "/notice/013-4738",
        "title": "Southampton Golf and Country Club Ltd.\n      \n         - Permit to take water",
        "comments_from_registry": 0,
        "comments_by_email": 0,
        "comments_by_mail": 0
    },
    "013-4878": {
        "url": "/notice/013-4878",
        "title": "Belmont Medical Centre Inc\n      \n         - Certificate of property use",
        "comments_from_registry": 0,
        "comments_by_email": 0,
        "comments_by_mail": 0
    },
    "013-4935": {
        "url": "/notice/013-4935",
        "title": "Tri City Materials Ltd.\n      \n         - Permit to take water",
        "comments_from_registry": 2,
        "comments_by_email": 0,
        "comments_by_mail": 0
    },
    "013-4886": {
        "url": "/notice/013-4886",
        "title": "Gowest Gold Ltd.\n      \n         - Permit to take water",
        "comments_from_registry": 0,
        "comments_by_email": 0,
        "comments_by_mail": 0
    },
    "019-0006": {
        "url": "/notice/019-0006",
        "title": "Circle K\n      \n         - Approval for variance from the Liquid Fuels Handling Code",
        "comments_from_registry": 0,
        "comments_by_email": 0,
        "comments_by_mail": 0
    },
    "013-4696": {
        "url": "/notice/013-4696",
        "title": "2528472 Ontario Incorporated\n      \n         - Environmental Compliance Approval (sewage)",
        "comments_from_registry": 0,
        "comments_by_email": 0,
        "comments_by_mail": 0
    },
    "019-0008": {
        "url": "/notice/019-0008",
        "title": "Husky Energy Inc\n      \n         - Approval for variance from the Liquid Fuels Handling Code",
        "comments_from_registry": 0,
        "comments_by_email": 0,
        "comments_by_mail": 0
    },
    "013-4356": {
        "url": "/notice/013-4356",
        "title": "BDM Developments (2016) Incorporated\n      \n         - Environmental Compliance Approval (sewage)",
        "comments_from_registry": 0,
        "comments_by_email": 0,
        "comments_by_mail": 0
    },
    "013-3476": {
        "url": "/notice/013-3476",
        "title": "Grant Castle Corp.\n      \n         - Environmental Compliance Approval (sewage)",
        "comments_from_registry": 0,
        "comments_by_email": 0,
        "comments_by_mail": 0
    },
    "013-3983": {
        "url": "/notice/013-3983",
        "title": "Township of Armour\n      \n         - Approval to amend a municipality\u2019s official plan",
        "comments_from_registry": 0,
        "comments_by_email": 0,
        "comments_by_mail": 0
    },
    "013-4291": {
        "url": "/notice/013-4291",
        "title": "857530 Ontario Inc. \n      \n         - Certificate of property use",
        "comments_from_registry": 0,
        "comments_by_email": 0,
        "comments_by_mail": 0
    },
    "013-4996": {
        "url": "/notice/013-4996",
        "title": "Alex Pleson\n      \n         - Mineral exploration permit",
        "comments_from_registry": 0,
        "comments_by_email": 0,
        "comments_by_mail": 0
    },
    "013-4830": {
        "url": "/notice/013-4830",
        "title": "O. Bettschen Construction Ltd. \n      \n         - Changes to the conditions of a licence to operate a pit or quarry",
        "comments_from_registry": 0,
        "comments_by_email": 0,
        "comments_by_mail": 0
    }
}