{
    "019-7510": {
        "url": "/notice/019-7510",
        "title": "William McKay\n      \n         - Approval for a consent (subject to conditions) in an area where there is no official plan in place",
        "comments_from_registry": 0,
        "comments_by_email": 0,
        "comments_by_mail": 0
    },
    "019-5660": {
        "url": "/notice/019-5660",
        "title": "Walker Aggregates Inc.\n      \n         - Changes to the site plan for a pit or quarry",
        "comments_from_registry": 6,
        "comments_by_email": 1,
        "comments_by_mail": 0
    },
    "019-7412": {
        "url": "/notice/019-7412",
        "title": "Mulmur Aggregates Inc.\n      \n         - Changes to the site plan for a pit or quarry",
        "comments_from_registry": 0,
        "comments_by_email": 0,
        "comments_by_mail": 0
    },
    "019-6365": {
        "url": "/notice/019-6365",
        "title": "Sika Canada Inc.\n      \n         - Environmental Compliance Approval (air)",
        "comments_from_registry": 0,
        "comments_by_email": 0,
        "comments_by_mail": 0
    },
    "019-7513": {
        "url": "/notice/019-7513",
        "title": "John Johnston\n      \n         - Approval for a consent (subject to conditions) in an area where there is no official plan in place",
        "comments_from_registry": 0,
        "comments_by_email": 0,
        "comments_by_mail": 0
    },
    "019-7194": {
        "url": "/notice/019-7194",
        "title": "TBT Engineering Limited\n      \n         - Approval for a consent (subject to conditions) in an area where there is no official plan in place",
        "comments_from_registry": 0,
        "comments_by_email": 0,
        "comments_by_mail": 0
    },
    "019-7439": {
        "url": "/notice/019-7439",
        "title": "Sittuk Investments Limited\n      \n         - Environmental Compliance Approval (sewage)",
        "comments_from_registry": 0,
        "comments_by_email": 0,
        "comments_by_mail": 0
    },
    "019-7168": {
        "url": "/notice/019-7168",
        "title": "RT Minerals Corporation\n      \n         - Mineral exploration permit",
        "comments_from_registry": 0,
        "comments_by_email": 0,
        "comments_by_mail": 0
    },
    "019-1385": {
        "url": "/notice/019-1385",
        "title": "Lafarge Canada Inc.\n      \n         - Environmental Compliance Approval (air)",
        "comments_from_registry": 0,
        "comments_by_email": 0,
        "comments_by_mail": 0
    },
    "019-7140": {
        "url": "/notice/019-7140",
        "title": "2247717 Ontario Ltd. operating as AAAA Sanitation\n      \n         - Environmental Compliance Approval (waste)",
        "comments_from_registry": 0,
        "comments_by_email": 0,
        "comments_by_mail": 0
    },
    "019-7409": {
        "url": "/notice/019-7409",
        "title": "A.L. Blair Construction Limited\n      \n         - Permit to take water",
        "comments_from_registry": 0,
        "comments_by_email": 0,
        "comments_by_mail": 0
    },
    "019-7668": {
        "url": "/notice/019-7668",
        "title": "Parkland Corporation \n      \n         - Approval for variance from the Liquid Fuels Handling Code",
        "comments_from_registry": 0,
        "comments_by_email": 0,
        "comments_by_mail": 0
    },
    "019-6629": {
        "url": "/notice/019-6629",
        "title": "2624492 ONTARIO INC.\n      \n         - Environmental Compliance Approval (air)",
        "comments_from_registry": 0,
        "comments_by_email": 0,
        "comments_by_mail": 0
    },
    "019-7202": {
        "url": "/notice/019-7202",
        "title": "2079610 Ontario Ltd. operating as Millcroft Golf Club\n      \n         - Permit to take water",
        "comments_from_registry": 0,
        "comments_by_email": 0,
        "comments_by_mail": 0
    },
    "019-7159": {
        "url": "/notice/019-7159",
        "title": "RT Minerals Corporation\n      \n         - Mineral exploration permit",
        "comments_from_registry": 0,
        "comments_by_email": 0,
        "comments_by_mail": 0
    },
    "019-7155": {
        "url": "/notice/019-7155",
        "title": "RT Minerals Corporation\n      \n         - Mineral exploration permit",
        "comments_from_registry": 0,
        "comments_by_email": 0,
        "comments_by_mail": 0
    },
    "019-6279": {
        "url": "/notice/019-6279",
        "title": "537 Kingston Road East (Ajax) Holdings ULC\n      \n         - Environmental Compliance Approval (sewage)",
        "comments_from_registry": 0,
        "comments_by_email": 0,
        "comments_by_mail": 0
    },
    "019-7387": {
        "url": "/notice/019-7387",
        "title": "RUTHERFORD LAND DEVELOPMENT CORP.\n      \n         - Permit to take water",
        "comments_from_registry": 0,
        "comments_by_email": 0,
        "comments_by_mail": 0
    },
    "019-7518": {
        "url": "/notice/019-7518",
        "title": "Juliada Holdings Inc.\n      \n         - Permit to take water",
        "comments_from_registry": 0,
        "comments_by_email": 0,
        "comments_by_mail": 0
    },
    "013-5072": {
        "url": "/notice/013-5072",
        "title": "Danford Construction Ltd.\n      \n         - Changes to the site plan for a pit or quarry",
        "comments_from_registry": 0,
        "comments_by_email": 0,
        "comments_by_mail": 0
    }
}