{
    "019-2128": {
        "url": "/notice/019-2128",
        "title": "Cambium Farms Ltd.\n      \n         - Environmental Compliance Approval (sewage)",
        "comments_from_registry": 0,
        "comments_by_email": 0,
        "comments_by_mail": 0
    },
    "012-6084": {
        "url": "/notice/012-6084",
        "title": "Niagara Escarpment Commission\n      \n         - Approval of an amendment to the Niagara Escarpment Plan",
        "comments_from_registry": 0,
        "comments_by_email": 105,
        "comments_by_mail": 0
    },
    "019-2677": {
        "url": "/notice/019-2677",
        "title": "Marc-Aurel Joseph McLean and Cedric McLean\n      \n         - Approval for a consent (subject to conditions) in an area where there is no official plan in place",
        "comments_from_registry": 0,
        "comments_by_email": 0,
        "comments_by_mail": 0
    },
    "019-1255": {
        "url": "/notice/019-1255",
        "title": "Parkbridge Lifestyle Communities Inc.\n      \n         - Environmental Compliance Approval (sewage)",
        "comments_from_registry": 0,
        "comments_by_email": 0,
        "comments_by_mail": 0
    },
    "019-1346": {
        "url": "/notice/019-1346",
        "title": "Regional Disposal Services Inc.\n      \n         - Environmental Compliance Approval (air)",
        "comments_from_registry": 0,
        "comments_by_email": 0,
        "comments_by_mail": 0
    },
    "019-2171": {
        "url": "/notice/019-2171",
        "title": "Specialty Polymer Coatings, Inc.\n      \n         - Environmental Compliance Approval (air)",
        "comments_from_registry": 0,
        "comments_by_email": 0,
        "comments_by_mail": 0
    },
    "019-2083": {
        "url": "/notice/019-2083",
        "title": "Sun-Brite Foods Inc.\n      \n         - Environmental Compliance Approval (sewage)",
        "comments_from_registry": 0,
        "comments_by_email": 0,
        "comments_by_mail": 0
    },
    "019-2620": {
        "url": "/notice/019-2620",
        "title": "Alexandre Richard\n      \n         - Environmental Compliance Approval (sewage)",
        "comments_from_registry": 0,
        "comments_by_email": 0,
        "comments_by_mail": 0
    },
    "019-1325": {
        "url": "/notice/019-1325",
        "title": "2443267 Ontario Limited\n      \n         - Environmental Compliance Approval (sewage)",
        "comments_from_registry": 0,
        "comments_by_email": 0,
        "comments_by_mail": 0
    },
    "019-0055": {
        "url": "/notice/019-0055",
        "title": "Gary Cake Septic\n      \n         - Environmental Compliance Approval (waste)",
        "comments_from_registry": 0,
        "comments_by_email": 0,
        "comments_by_mail": 0
    },
    "019-0059": {
        "url": "/notice/019-0059",
        "title": "1447128 Ontario Limited o/a Shamrock Septic Service\n      \n         - Environmental Compliance Approval (waste)",
        "comments_from_registry": 0,
        "comments_by_email": 0,
        "comments_by_mail": 0
    },
    "019-0062": {
        "url": "/notice/019-0062",
        "title": "Kevin Blaney o/a Ks and B Septic \n      \n         - Environmental Compliance Approval (waste)",
        "comments_from_registry": 0,
        "comments_by_email": 0,
        "comments_by_mail": 0
    },
    "013-4945": {
        "url": "/notice/013-4945",
        "title": "Chadwick Gordron Munro\n      \n         - Environmental Compliance Approval (waste)",
        "comments_from_registry": 0,
        "comments_by_email": 0,
        "comments_by_mail": 0
    },
    "013-4946": {
        "url": "/notice/013-4946",
        "title": "John Hedican Enterprises/EnviroClean\n      \n         - Environmental Compliance Approval (waste)",
        "comments_from_registry": 0,
        "comments_by_email": 0,
        "comments_by_mail": 0
    },
    "019-2670": {
        "url": "/notice/019-2670",
        "title": "Infrastructure Ontario\n      \n         - Permit for activities to achieve an overall benefit to a species",
        "comments_from_registry": 3,
        "comments_by_email": 0,
        "comments_by_mail": 0
    },
    "019-1463": {
        "url": "/notice/019-1463",
        "title": "Thomas Houston Courtice Septic\n      \n         - Environmental Compliance Approval (waste)",
        "comments_from_registry": 0,
        "comments_by_email": 0,
        "comments_by_mail": 0
    },
    "011-2912": {
        "url": "/notice/011-2912",
        "title": "Technical Guidance: Soil Vapour Intrusion Assessment",
        "comments_from_registry": 5,
        "comments_by_email": 7,
        "comments_by_mail": 0
    },
    "019-2607": {
        "url": "/notice/019-2607",
        "title": "Clear Lake Estates Corp. (2555569 Ontario Inc.)\n      \n         - Permit for activities to achieve an overall benefit to a species",
        "comments_from_registry": 0,
        "comments_by_email": 0,
        "comments_by_mail": 0
    },
    "019-2758": {
        "url": "/notice/019-2758",
        "title": "SUNCOR ENERGY PRODUCTS PARTNERSHIP\n      \n         - Approval for variance from the Liquid Fuels Handling Code",
        "comments_from_registry": 0,
        "comments_by_email": 0,
        "comments_by_mail": 0
    },
    "019-0997": {
        "url": "/notice/019-0997",
        "title": "Lafarge Canada Inc.\n      \n         - Environmental Compliance Approval (sewage)",
        "comments_from_registry": 0,
        "comments_by_email": 0,
        "comments_by_mail": 0
    }
}